demo_book/__init__.py
demo_book-0.0.1.dist-info/LICENSE
demo_book-0.0.1.dist-info/WHEEL
demo_book-0.0.1.dist-info/METADATA
demo_book-0.0.1.dist-info/RECORD
